odoo/addons/account_invoice_report_hide_triple_disc_by_partner/README.rst
odoo/addons/account_invoice_report_hide_triple_disc_by_partner/__init__.py
odoo/addons/account_invoice_report_hide_triple_disc_by_partner/__manifest__.py
odoo/addons/account_invoice_report_hide_triple_disc_by_partner/readme/CONTRIBUTORS.rst
odoo/addons/account_invoice_report_hide_triple_disc_by_partner/readme/DESCRIPTION.rst
odoo/addons/account_invoice_report_hide_triple_disc_by_partner/reports/report_invoice.xml
odoo/addons/account_invoice_report_hide_triple_disc_by_partner/static/description/icon.png
odoo/addons/account_invoice_report_hide_triple_disc_by_partner/static/description/index.html
odoo_addon_account_invoice_report_hide_triple_disc_by_partner-16.0.1.0.0.1.dist-info/METADATA
odoo_addon_account_invoice_report_hide_triple_disc_by_partner-16.0.1.0.0.1.dist-info/WHEEL
odoo_addon_account_invoice_report_hide_triple_disc_by_partner-16.0.1.0.0.1.dist-info/top_level.txt
odoo_addon_account_invoice_report_hide_triple_disc_by_partner-16.0.1.0.0.1.dist-info/RECORD
