Metadata-Version: 2.1
Name: odoo-addon-account_invoice_report_hide_triple_disc_by_partner
Version: 16.0.1.0.0.1
Summary: Do not show triple discount in invoices
Home-page: https://github.com/sygel-technology/sy-account-invoice-reporting
Author: Sygel, Odoo Community Association (OCA)
Author-email: support@odoo-community.org
License: AGPL-3
Classifier: Programming Language :: Python
Classifier: Framework :: Odoo
Classifier: Framework :: Odoo :: 16.0
Classifier: License :: OSI Approved :: GNU Affero General Public License v3
Requires-Python: >=3.10
Requires-Dist: odoo-addon-account-invoice-report-hide-discounts-by-partner<16.1dev,>=16.0dev
Requires-Dist: odoo-addon-account-invoice-triple-discount<16.1dev,>=16.0dev
Requires-Dist: odoo<16.1dev,>=16.0a
